simple_graph_retriever/__init__.py
simple_graph_retriever/client.py
simple_graph_retriever/config.py
simple_graph_retriever/indexer.py
simple_graph_retriever/models.py
simple_graph_retriever/retriever.py
simple_graph_retriever-1.0.0rc11.dist-info/METADATA
simple_graph_retriever-1.0.0rc11.dist-info/WHEEL
simple_graph_retriever-1.0.0rc11.dist-info/RECORD
