Metadata-Version: 2.4
Name: simple-graph-retriever
Version: 1.0.0rc11
Summary: A simple graph-based retriever using Neo4j and Qdrant
Author-email: Victor de La Salmonière <victor@lettria.com>
Classifier: License :: OSI Approved :: MIT License
Classifier: Operating System :: OS Independent
Classifier: Programming Language :: Python :: 3
Requires-Python: >=3.8
Requires-Dist: igraph
Requires-Dist: leidenalg
Requires-Dist: neo4j
Requires-Dist: pydantic
Requires-Dist: pydantic-settings
Requires-Dist: qdrant-client==1.11.0
Requires-Dist: requests
Requires-Dist: tqdm
